odoo/addons/l10n_us_gaap_mis_report/README.rst
odoo/addons/l10n_us_gaap_mis_report/__init__.py
odoo/addons/l10n_us_gaap_mis_report/__manifest__.py
odoo/addons/l10n_us_gaap_mis_report/data/mis_report_balance_sheet.xml
odoo/addons/l10n_us_gaap_mis_report/data/mis_report_income_statement.xml
odoo/addons/l10n_us_gaap_mis_report/data/mis_report_styles.xml
odoo/addons/l10n_us_gaap_mis_report/docs/l10n_us_gaap_balance_sheet.ods
odoo/addons/l10n_us_gaap_mis_report/docs/l10n_us_gaap_income_statement.ods
odoo/addons/l10n_us_gaap_mis_report/i18n/es.po
odoo/addons/l10n_us_gaap_mis_report/i18n/l10n_us_gaap_mis_report.pot
odoo/addons/l10n_us_gaap_mis_report/readme/CONFIGURE.md
odoo/addons/l10n_us_gaap_mis_report/readme/CONTRIBUTORS.md
odoo/addons/l10n_us_gaap_mis_report/readme/DESCRIPTION.md
odoo/addons/l10n_us_gaap_mis_report/readme/INSTALL.md
odoo/addons/l10n_us_gaap_mis_report/static/description/icon.png
odoo/addons/l10n_us_gaap_mis_report/static/description/index.html
odoo_addon_l10n_us_gaap_mis_report-17.0.1.0.0.2.dist-info/METADATA
odoo_addon_l10n_us_gaap_mis_report-17.0.1.0.0.2.dist-info/WHEEL
odoo_addon_l10n_us_gaap_mis_report-17.0.1.0.0.2.dist-info/top_level.txt
odoo_addon_l10n_us_gaap_mis_report-17.0.1.0.0.2.dist-info/RECORD
