Metadata-Version: 2.1
Name: odoo-addon-l10n_us_gaap_mis_report
Version: 17.0.1.0.0.2
Requires-Python: >=3.10
Requires-Dist: odoo-addon-l10n_us_gaap>=17.0dev,<17.1dev
Requires-Dist: odoo-addon-mis_builder>=17.0dev,<17.1dev
Requires-Dist: odoo>=17.0a,<17.1dev
Summary: MIS Builder Templates for US Chart of Accounts
Home-page: https://github.com/OCA/l10n-usa
License: AGPL-3
Author: ForgeFlow, Odoo Community Association (OCA)
Author-email: support@odoo-community.org
Classifier: Programming Language :: Python
Classifier: Framework :: Odoo
Classifier: Framework :: Odoo :: 17.0
Classifier: License :: OSI Approved :: GNU Affero General Public License v3
Classifier: Development Status :: 5 - Production/Stable
